ttads/__init__.py
ttads/server.py
ttads/tunnel.py
ttads/version
ttads-0.1.1.dist-info/METADATA
ttads-0.1.1.dist-info/WHEEL
ttads-0.1.1.dist-info/entry_points.txt
ttads-0.1.1.dist-info/top_level.txt
ttads-0.1.1.dist-info/RECORD
