Metadata-Version: 2.1
Name: ttads
Version: 0.1.1
Summary: A development server for Tasmota Berry Application (TAPP) apps
Home-page: https://link.frontmatter.ai/ttads
Author: Frontmatter
License: Copyright © 2023 Frontmatter. All rights reserved.
Keywords: development berry script tasmota tapp
Platform: UNKNOWN
Requires-Dist: click
Requires-Dist: flask
Requires-Dist: pyngrok
Requires-Dist: pyyaml
